dataframe_api/__init__.py
dataframe_api/column_object.py
dataframe_api/dataframe_object.py
dataframe_api/dtypes.py
dataframe_api/groupby_object.py
dataframe_api/py.typed
dataframe_api/scalar_object.py
dataframe_api/typing.py
dataframe_api-2023.10b0.dist-info/METADATA
dataframe_api-2023.10b0.dist-info/WHEEL
dataframe_api-2023.10b0.dist-info/RECORD
